<annotation><filename>2010_006093.jpg</filename><folder>amt</folder><source><sourceImage>The MIT-CSAIL database of objects and scenes</sourceImage><sourceAnnotation>LabelMe Webtool</sourceAnnotation></source><object><name>boy</name><deleted>0</deleted><verified>0</verified><date>11-Mar-2012 22:19:30</date><id>0</id><polygon><username>anonymous</username><pt><x>418</x><y>105</y></pt><pt><x>428</x><y>95</y></pt><pt><x>432</x><y>84</y></pt><pt><x>439</x><y>78</y></pt><pt><x>440</x><y>71</y></pt><pt><x>440</x><y>67</y></pt><pt><x>449</x><y>52</y></pt><pt><x>442</x><y>34</y></pt><pt><x>435</x><y>24</y></pt><pt><x>420</x><y>22</y></pt><pt><x>402</x><y>21</y></pt><pt><x>387</x><y>22</y></pt><pt><x>374</x><y>39</y></pt><pt><x>374</x><y>56</y></pt><pt><x>375</x><y>64</y></pt><pt><x>371</x><y>65</y></pt><pt><x>374</x><y>73</y></pt><pt><x>377</x><y>77</y></pt><pt><x>382</x><y>81</y></pt><pt><x>382</x><y>91</y></pt><pt><x>378</x><y>96</y></pt><pt><x>374</x><y>98</y></pt><pt><x>362</x><y>101</y></pt><pt><x>351</x><y>104</y></pt><pt><x>340</x><y>111</y></pt><pt><x>327</x><y>119</y></pt><pt><x>322</x><y>138</y></pt><pt><x>319</x><y>169</y></pt><pt><x>319</x><y>195</y></pt><pt><x>322</x><y>215</y></pt><pt><x>348</x><y>230</y></pt><pt><x>372</x><y>240</y></pt><pt><x>378</x><y>218</y></pt><pt><x>389</x><y>183</y></pt><pt><x>464</x><y>178</y></pt><pt><x>462</x><y>169</y></pt><pt><x>466</x><y>154</y></pt><pt><x>458</x><y>137</y></pt><pt><x>451</x><y>127</y></pt><pt><x>440</x><y>116</y></pt><pt><x>426</x><y>111</y></pt></polygon></object><object><name>laptop</name><deleted>0</deleted><verified>0</verified><date>11-Mar-2012 22:19:30</date><id>1</id><polygon><username>anonymous</username><pt><x>336</x><y>239</y></pt><pt><x>364</x><y>293</y></pt><pt><x>371</x><y>298</y></pt><pt><x>500</x><y>295</y></pt><pt><x>501</x><y>177</y></pt><pt><x>389</x><y>186</y></pt><pt><x>374</x><y>234</y></pt></polygon></object><object><name>gate</name><deleted>0</deleted><verified>0</verified><date>11-Mar-2012 22:19:30</date><id>2</id><polygon><username>anonymous</username><pt><x>249</x><y>1</y></pt><pt><x>248</x><y>240</y></pt><pt><x>353</x><y>236</y></pt><pt><x>498</x><y>180</y></pt><pt><x>499</x><y>1</y></pt></polygon></object><object><name>window</name><deleted>0</deleted><verified>0</verified><date>11-Mar-2012 22:19:30</date><id>3</id><polygon><username>anonymous</username><pt><x>105</x><y>109</y></pt><pt><x>99</x><y>0</y></pt><pt><x>0</x><y>0</y></pt><pt><x>0</x><y>110</y></pt></polygon></object><imagesize><nrows>375
</nrows><ncols>500
</ncols></imagesize></annotation>